Workbook

Sheet Portada
B2: D-PAY 3.0 — Catálogo de Requerimientos No Funcionales
B4: Clasificación ISO/IEC 25010 · el DAS 1.0.2 manda · DoD/repo/DOC-07 como alias y evidencia
B6: Proyecto | C6: D-PAY 3.0 — POS móvil multi-pasarela (DTemite)
B7: Asignatura | C7: Capstone PTY4614 / APT122 — Duoc UC 2026-2
B8: Documento | C8: Catálogo RNF (anexo del DAS §Metas y §Escenarios)
B9: Versión | C9: 1.0.2
B10: Fecha | C10: 2026-10-16
B11: Elaborado por | C11: Reinhartd Munzenmayer (QA)
B12: Revisa | C12: Diego Madrid (arquitectura) · Pablo Gutiérrez (Scrum Master)
B13: Aprueba | C13: José Robles Rocha (Product Owner, DTemite)
B14: Fuente de arquitectura | C14: DAS 1.0.2 . IDs RNF-xx.y: desglose de este catálogo. DoD v1.0, repo y Fase 1 = alias.
B15: Línea base | C15: D-PAY 2.0: cobro Kozen + TUU en producción, operado por Diego Madrid. D-PAY 3.0 lo extiende con Webpay en celular genérico.
B16: Restricciones | C16: Sin Docker · sin NFC/SoftPOS · sin PAN/CVV en dispositivo · monolito por capas
B19: Hojas del libro
B20: Catálogo RNF | C20: Requerimientos con tipo, ISO 25010, métrica, criterio, alcance, evidencia y estado.
B21: Escenarios DAS | C21: Escenarios de calidad (fuente, estímulo, artefacto, ambiente, respuesta, medida).
B22: Contraste | C22: Diferencias DAS (manda) ↔ DoD/repo/Fase 1. Acción = alinear el catálogo; el DAS no se edita.
B23: Ambigüedades | C23: Revisión estática (formato planilla 1.3.4 de Calidad de Software).
B24: Rúbrica Fase 2 | C24: Aporte del catálogo a cada indicador de evaluación.
B25: Control | C25: Tablero de conteos por tipo y estado.
B26: Listas | C26: Valores permitidos para las validaciones.

Sheet Catálogo RNF
A1: Catálogo RNF — D-PAY 3.0
A2: ISO/IEC 25010 · DAS 1.0.2 manda · versión 1.0.1 · 2026-10-12
A4: ID | B4: Tipo | C4: Característica ISO 25010 | D4: Subcaracterística | E4: Nombre | F4: Enunciado (el sistema debe…) | G4: Métrica / indicador | H4: Criterio de aceptación | I4: MoSCoW | J4: Alcance | K4: HU / CA / CU | L4: Meta o escenario DAS | M4: Caso de prueba | N4: Evidencia | O4: Estado verificación | P4: Responsable | Q4: Fuente | R4: Alias (otros docs) | S4: Observación
A5: RNF-01.1 | B5: rendimiento | C5: Eficiencia de desempeño | D5: Comportamiento temporal | E5: Login rápido | F5: El sistema debe completar el inicio de sesión del cajero en red móvil 4G en menos de 3 segundos. | G5: Segundos desde «Ingresar» hasta la pantalla principal de venta. | H5: Peor muestra < 3 s en 4G (5 muestras). | I5: Must | J5: Ambos | K5: CU-01 | L5: Meta Desempeño | M5: MTC login (DOC-07 03_Rendimiento) | N5: metricas-celular-android-20260927.txt | O5: OK | P5: Reinhartd Munzenmayer | Q5: DAS 1.0.2 Meta Desempeño | R5: DoD v1.0 · Repo RNF-01.1 · Fase 1 RNF-01.1 | S5: 2,5 s en 4G primer login (27/09) en celular Android. Una muestra por escenario: completar 5 para cumplir el criterio.
A6: RNF-01.2 | B6: rendimiento | C6: Eficiencia de desempeño | D6: Comportamiento temporal | E6: Inicio de cobro TUU | F6: En terminal Kozen, el sistema debe lanzar el Intent de la app TUU en menos de 2 segundos tras confirmar el monto. | G6: Segundos desde «Confirmar monto» hasta la pantalla TUU. | H6: < 2 s en P8 Neo con TUU instalada. | I6: Must | J6: D-PAY 2.0 Kozen | K6: HU-02 · HU-06 · CU-03 | L6: Fuera del DAS (umbral < 2 s no figura; CU-03 / Hardware TUU sí) | M6: TC-064 regresión TUU | N6: COD-08-HU06-tuu-kozen/capturas/TC-RG-01*; 07_Plan_de_Pruebas/05_Evidencias_por_sprint/Sprint_03/capturas_20261013/; jest-hu06Tuu-factory-deteccion-output-20261011.txt | O6: Parcial | P6: Diego Madrid | Q6: DoD v1.0 (fuera del DAS) | R6: Repo RNF-01.2 | S6: Parcial 13/10/2026: Diego Madrid, Kozen P8 Neo. Débito $2.000 aprobado; crédito $5.000 cancelado (no declined emisor). Falta crédito aprobado. Jest 17/17 (11/10).
A7: RNF-01.3 | B7: rendimiento | C7: Eficiencia de desempeño | D7: Comportamiento temporal | E7: Carga de catálogo | F7: El sistema debe cargar un catálogo de hasta 500 productos en menos de 5 segundos. | G7: Segundos hasta lista de productos navegable. | H7: < 5 s con 500 productos. | I7: Should | J7: Ambos | K7: CU-02 | L7: Meta Desempeño («catálogo usable en terreno»; 500 / < 5 s no figuran en el DAS) | M7: MTC catálogo | N7: metricas-celular-android-20260927.txt | O7: Parcial | P7: Reinhartd Munzenmayer | Q7: DoD v1.0 (umbral fuera del DAS) | R7: Repo RNF-01.3 | S7: 1,0 s medido en celular Android (27/09); no consta catálogo de 500 productos. El umbral 500 / < 5 s es del DoD, no del DAS.
A8: RNF-01.4 | B8: rendimiento | C8: Eficiencia de desempeño | D8: Comportamiento temporal | E8: Emisión de DTE | F8: El sistema debe emitir el DTE, incluida la firma, en menos de 15 segundos desde la confirmación de la venta. | G8: Segundos desde confirmar venta hasta folio asignado. | H8: Promedio de 5 muestras ≤ 15 s (EC-RNF-02). | I8: Should | J8: Ambos | K8: CU-04 | L8: EC-RNF-02 | M8: MTC DTE (Sprint 3) | N8: — | O8: No ejecutado | P8: Reinhartd Munzenmayer | Q8: DAS 1.0.2 EC-RNF-02 | R8: DoD v1.0 · Repo RNF-01.4 · (Fase 1 usaba RNF-01.4 para Webpay) | S8: Pendiente boleta tipo 39 estable en Sprint 3.
A9: RNF-01.5 | B9: rendimiento | C9: Eficiencia de desempeño | D9: Comportamiento temporal | E9: Apertura checkout Webpay | F9: Con el proxy en la red local, el sistema debe dejar abierto el checkout Webpay en menos de 10 segundos tras confirmar la tarjeta. | G9: Segundos desde escanear QR / confirmar hasta formulario Transbank. | H9: < 10 s, 5 muestras en Wi-Fi LAN. | I9: Should | J9: D-PAY 3.0 Capstone | K9: HU-03 · CA-WP.1 | L9: Fuera del DAS | M9: MTC-13 | N9: metricas-celular-android-webpay-20261004.txt | O9: Parcial | P9: Reinhartd Munzenmayer | Q9: DoD v1.0 (fuera del DAS) | R9: Fase 1 RNF-01.4 · no existe en repo | S9: ~10 s en 2 muestras (04/10) en celular Android. El DAS incluye Webpay (CU-03, ADR-07) sin umbral de 10 s. El «10 s» del DAS es «8–10 servicios», no checkout. No se propone cambio al DAS 1.0.2.
A10: RNF-02.1 | B10: seguridad | C10: Seguridad | D10: Confidencialidad | E10: Token de sesión en MMKV | F10: El sistema debe guardar el token de sesión en MMKV y nunca en AsyncStorage plano. | G10: Ubicación de persistencia del token. | H10: Inspección de código y almacenamiento: 0 tokens en AsyncStorage. | I10: Must | J10: Ambos | K10: CU-01 | L10: EC-RNF-03 · ADR-03 | M10: TC-SEC (DOC-07 04_Seguridad) | N10: EVIDENCIA_COD-03-05_AUDITORIA_2026-09-11.md | O10: OK | P10: Reinhartd Munzenmayer | Q10: DAS 1.0.2 EC-RNF-03 · ADR-03 · ADR-04 | R10: DoD v1.0 · Repo RNF-02.1 · Fase 1 RNF-02.1 («JWT»)
A11: RNF-02.2 | B11: seguridad | C11: Seguridad | D11: Confidencialidad | E11: Contraseña protegida | F11: El sistema nunca debe almacenar ni registrar la contraseña en texto plano. | G11: Ocurrencias de contraseña en almacenamiento o logs. | H11: 0 ocurrencias en MMKV, logs y repositorio. | I11: Must | J11: Ambos | K11: CU-01 | L11: EC-RNF-03 | M11: TC-SEC | N11: EVIDENCIA_COD-03-05_AUDITORIA_2026-09-11.md | O11: OK | P11: Reinhartd Munzenmayer | Q11: DAS 1.0.2 EC-RNF-03 | R11: DoD v1.0 · Repo RNF-02.2
A12: RNF-02.3 | B12: seguridad | C12: Seguridad | D12: Integridad | E12: HTTPS hacia API DTemite | F12: El sistema debe comunicarse con la API de DTemite solo por HTTPS. | G12: Protocolo de cada endpoint productivo/QA. | H12: 100 % de llamadas a la API DTemite por HTTPS. | I12: Must | J12: Ambos | K12: CU-01 · CU-04 | L12: Meta Seguridad | M12: TC-SEC | N12: Auditoría COD-03 | O12: OK | P12: Reinhartd Munzenmayer | Q12: DAS 1.0.2 Meta Seguridad | R12: DoD v1.0 · Repo RNF-02.3 | S12: HTTPS, sin versión TLS. TLS 1.2+ es operacionalización del catálogo, no del DAS. El proxy Webpay académico corre en HTTP LAN (TC-WP-HTTP); queda fuera de este RNF. Para WWAN usar túnel HTTPS.
A13: RNF-02.4 | B13: seguridad | C13: Seguridad | D13: Confidencialidad | E13: Sin PAN ni CVV | F13: El sistema no debe almacenar PAN ni CVV en el dispositivo, en el proxy ni en el repositorio; el dato de tarjeta solo lo ven TUU o Transbank. | G13: Ocurrencias de PAN/CVV en almacenamiento, SQLite proxy, logs y Git. | H13: 0 ocurrencias (grep + inspección SQLite). | I13: Must | J13: Ambos | K13: CA-WP.2 · HU-06 | L13: EC-RNF-03 · ADR-05 · ADR-07 | M13: TC-SEC · TC-WP-TBK | N13: Auditoría COD-03 · capturas TBK 04/10 | O13: OK | P13: Reinhartd Munzenmayer | Q13: DAS 1.0.2 EC-RNF-03 · ADR-05 · ADR-07 | R13: DoD v1.0 · Repo RNF-02.4 · Fase 1 RNF-02.4 | S13: Sin PAN/CVV. PCI-DSS; ver también RNF-08.2.
A14: RNF-02.5 | B14: seguridad | C14: Seguridad | D14: Responsabilidad | E14: Secretos fuera de Git | F14: El keystore, los .env y las credenciales del proxy deben quedar fuera del repositorio. | G14: Archivos sensibles versionados. | H14: 0 secretos en historial Git (escaneo). | I14: Must | J14: Ambos | K14: CA-WP.2 | L14: Restricción «Repositorio académico» | M14: TC-SEC | N14: Auditoría COD-03 | O14: OK | P14: Reinhartd Munzenmayer | Q14: DAS 1.0.2 restricción «Repositorio académico» | R14: DoD v1.0 · Repo RNF-02.5
A15: RNF-02.6 | B15: seguridad | C15: Seguridad | D15: Autenticidad | E15: API keys del Hub hasheadas | F15: La plataforma debe almacenar hasheadas las API keys del Payment Hub. | G15: Formato de almacenamiento de las keys. | H15: Keys no recuperables en claro desde la BD. | I15: Must (plataforma) | J15: Plataforma DTemite | K15: CU-08 | L15: Fuera del DAS | M15: — | N15: — | O15: N/A | P15: Diego Madrid | Q15: 04-requerimientos (fuera del DAS) | R15: Solo en repo (no en DoD ni en el DAS) | S15: No figura en el DAS 1.0.2. Responsabilidad del backend DTemite; QA Capstone no lo verifica.
A16: RNF-03.1 | B16: disponibilidad | C16: Fiabilidad | D16: Disponibilidad / Recuperabilidad | E16: Venta en efectivo sin conexión | F16: Sin conexión, el sistema debe permitir armar y cobrar una venta en efectivo, dejarla en cola local y reintentar la sincronización al volver la red, sin perder el carrito. | G16: Ventas perdidas por corte de red. | H16: 0 carritos perdidos; sincroniza al recuperar red (EC-RNF-04). | I16: Should | J16: Ambos | K16: CU-02 · CU-05 | L16: EC-RNF-04 | M16: TC-RNF03 | N16: regresion-efectivo-dte/ (27/09) | O16: Parcial | P16: Reinhartd Munzenmayer | Q16: DAS 1.0.2 EC-RNF-04 | R16: DoD v1.0 · Repo RNF-03.1 + RNF-03.2 · Fase 1 RNF-03.1 | S16: Venta offline OK (folio 0, PDF local). Falta evidencia del reintento automático de sincronización. Alineado con el DAS (cola local, 0 carritos perdidos).
A17: RNF-03.2 | B17: disponibilidad | C17: Fiabilidad | D17: Tolerancia a fallos | E17: Pagos fallidos identificables | F17: Las transacciones fallidas de TUU y de Webpay deben quedar identificables y nunca mostrarse como cobro exitoso. | G17: Estados declined/cancelled/timeout mostrados como éxito. | H17: 0 falsos positivos en rechazo, cancelación y timeout. | I17: Must | J17: Ambos | K17: CA-WP.4 · CA-WP.6 | L17: Fuera del DAS | M17: TC-WP-04 · TC-WP-05 | N17: CLASIFICACION-CAPTURAS-2026-10-04.md | O17: OK | P17: Reinhartd Munzenmayer | Q17: DoD v1.0 (fuera del DAS) | R17: Repo RNF-03.3 («auditables») | S17: No modelado en el DAS 1.0.2. Rechazo MC y cancelación verificados en celular Android (04/10).
A18: RNF-04.1 | B18: usabilidad | C18: Usabilidad (Interacción) | D18: Protección frente a errores | E18: Mensajes en español | F18: Los errores de pago y de DTE deben mostrarse en español y en lenguaje del cajero. | G18: Mensajes de error sin traducir o técnicos. | H18: 100 % de mensajes de pago/DTE en español. | I18: Must | J18: Ambos | K18: CA-WP.4 | L18: Meta Usabilidad · EC-RNF-01 | M18: TC-WP-04 · MTC-10 | N18: Capturas 04/10 («Pago no completado») | O18: OK | P18: Reinhartd Munzenmayer | Q18: DAS 1.0.2 Meta Usabilidad · EC-RNF-01 | R18: DoD v1.0 · Repo RNF-04.2
A19: RNF-04.2 | B19: usabilidad | C19: Usabilidad (Interacción) | D19: Operabilidad | E19: UI táctil para POS | F19: La interfaz debe ser operable con el dedo en pantallas de 5" a 6". | G19: Controles por debajo del tamaño táctil mínimo. | H19: Flujo de venta completo operable en celular Android y P8 Neo. | I19: Must | J19: Ambos | K19: CU-02 · CU-03 | L19: EC-RNF-01 (ambiente 5"–6") | M19: Sesiones celular Android | N19: Capturas celular Android 19/09–04/10 | O19: OK | P19: Reinhartd Munzenmayer | Q19: DAS 1.0.2 EC-RNF-01 | R19: 04-requerimientos · Repo RNF-04.1 · no en DoD | S19: El DAS cita UI táctil POS y pantalla 5"–6". El ID 04.2 es desglose del catálogo.
A20: RNF-04.3 | B20: usabilidad | C20: Usabilidad (Interacción) | D20: Operabilidad | E20: Venta rápida | F20: El cajero debe poder completar una venta en efectivo con boleta en menos de 2 minutos en prueba guiada. | G20: Minutos por venta efectivo + boleta. | H20: < 2 min (EC-RNF-01). | I20: Should | J20: Ambos | K20: CU-02 · CU-04 | L20: EC-RNF-01 | M20: MTC usabilidad (por crear) | N20: — | O20: No ejecutado | P20: Reinhartd Munzenmayer | Q20: DAS 1.0.2 EC-RNF-01 | R20: Repo RNF-04.3 («pocos taps») | S20: Alineado con la medida del DAS (< 2 min). El repo decía «pocos taps» (ambiguo).
A21: RNF-04.4 | B21: usabilidad | C21: Usabilidad (Interacción) | D21: Estética de la interfaz | E21: Tema claro y oscuro | F21: El sistema debe ofrecer tema claro y oscuro configurable. | G21: Pantallas sin soporte de tema. | H21: Tema aplicable desde configuración. | I21: Could | J21: Ambos | K21: CU-09 | L21: CU-09 | M21: — | N21: — | O21: No ejecutado | P21: Reinhartd Munzenmayer | Q21: DAS 1.0.2 CU-09 | R21: 04-requerimientos · Repo RNF-04.4 | S21: El DAS CU-09 menciona tema claro/oscuro. RF-08.3 lo declara implementado; falta evidencia.
A22: RNF-05.1 | B22: portabilidad | C22: Flexibilidad (Portabilidad) | D22: Adaptabilidad | E22: Android 7.0 o superior | F22: El sistema debe ejecutarse en Android API 24 (7.0) o superior. | G22: minSdkVersion del build. | H22: minSdkVersion = 24. | I22: Must | J22: Ambos | K22: HU-01 | L22: Ámbito «Plataformas» | M22: Revisión de build | N22: android/build.gradle (minSdkVersion = 24) | O22: OK | P22: Reinhartd Munzenmayer | Q22: DAS 1.0.2 Ámbito «Plataformas» | R22: DoD v1.0 · Repo RNF-05.1 · Fase 1 RNF-05.1 | S22: Alineado con el DAS: Android 7.0+ (API 24).
A23: RNF-05.2 | B23: portabilidad | C23: Compatibilidad | D23: Interoperabilidad | E23: Terminal Kozen P8 Neo | F23: El camino TUU debe funcionar en Kozen P8 Neo (armeabi-v7a). | G23: ABI incluida en el APK y cobro TUU. | H23: APK con armeabi-v7a; cobro TUU aprobado en P8 Neo. | I23: Must | J23: D-PAY 2.0 Kozen | K23: HU-01 · HU-06 | L23: Restricción «Hardware TUU» | M23: TC-064 | N23: COD-08-HU06-tuu-kozen/capturas/TC-RG-01*; 07_Plan_de_Pruebas/05_Evidencias_por_sprint/Sprint_03/capturas_20261013/; jest-hu06Tuu-factory-deteccion-output-20261011.txt | O23: Parcial | P23: Diego Madrid | Q23: DAS 1.0.2 restricción «Hardware TUU» | R23: DoD v1.0 · Repo RNF-05.2 · Fase 1 RNF-05.2 | S23: Parcial 13/10/2026: Diego Madrid, Kozen P8 Neo. Débito $2.000 aprobado; crédito $5.000 cancelado (no declined emisor). Falta crédito aprobado. Jest 17/17 (11/10).
A24: RNF-05.3 | B24: portabilidad | C24: Flexibilidad (Portabilidad) | D24: Adaptabilidad | E24: Celular Android genérico | F24: En un smartphone Android sin TUU (API 24+), el sistema debe operar efectivo, DTE y Webpay. | G24: Flujos disponibles en perfil GENERIC_MOBILE. | H24: Perfil GENERIC_MOBILE detectado y cobro Webpay aprobado. | I24: Must | J24: D-PAY 3.0 Capstone | K24: HU-01 · HU-03 · HU-04 | L24: Restricción «Hardware TUU» · Ámbito Android 7.0+ (API 24) | M24: TC-DEV · TC-WP-TBK | N24: Comprobante celular Android $2.000 (04/10) | O24: OK | P24: Reinhartd Munzenmayer | Q24: DAS 1.0.2 Ámbito / Hardware TUU | R24: DoD v1.0 · Repo RNF-05.3 (alias Android 10+ descartado) | S24: El DAS fija Android 7.0+ (API 24) para Kozen y smartphone. El alias «Android 10+» del repo queda descartado.
A25: RNF-05.4 | B25: portabilidad | C25: Flexibilidad (Portabilidad) | D25: Adaptabilidad | E25: Cliente iOS | F25: No se desarrolla cliente iOS en el MVP. | G25: — | H25: — | I25: Won't | J25: Ambos | K25: — | L25: Ámbito «Excluye» | M25: — | N25: — | O25: N/A | P25: — | Q25: DAS 1.0.2 Ámbito «Excluye» | R25: 04-requerimientos · Repo RNF-05.4 · RF-W03 | S25: Alineado con el DAS: cliente iOS nativo excluido.
A26: RNF-06.1 | B26: mantenibilidad | C26: Mantenibilidad | D26: Analizabilidad | E26: TypeScript estricto | F26: El código debe compilar con TypeScript en modo estricto. | G26: Errores de tsc. | H26: strict activo y 0 errores de tsc. | I26: Must | J26: Ambos | K26: — | L26: EC-RNF-05 | M26: Revisión de configuración | N26: tsconfig.json extiende @react-native/typescript-config (strict) | O26: OK | P26: Pablo Gutiérrez | Q26: DAS 1.0.2 EC-RNF-05 · Meta Modificabilidad | R26: 04-requerimientos · Repo RNF-06.1 | S26: Alineado con el DAS: TypeScript estricto.
A27: RNF-06.2 | B27: mantenibilidad | C27: Mantenibilidad | D27: Modularidad | E27: Capas screens / stores / services | F27: El código debe separar screens, stores y services (DAS). En el Capstone, las pasarelas implementan el contrato PaymentGateway. | G27: Separación de capas; pasarelas fuera del contrato Capstone. | H27: Capas verificables; factory resuelve TUU/Webpay/Mock (regla HU-02, no texto del DAS). | I27: Must | J27: Ambos | K27: HU-02 | L27: EC-RNF-05 · Meta Modificabilidad | M27: Jest PaymentGatewayFactory | N27: PaymentGatewayFactory.test.ts (9/9) | O27: OK | P27: Pablo Gutiérrez | Q27: DAS 1.0.2 EC-RNF-05 | R27: 04-requerimientos · Repo RNF-06.2 | S27: IPaymentGateway y «no tocar SalePaymentScreen» son regla Capstone (HU-02), no texto del DAS 1.0.2.
A28: RNF-06.3 | B28: mantenibilidad | C28: Mantenibilidad | D28: Modificabilidad | E28: Contrato API documentado | F28: Los endpoints que consume el POS deben estar documentados. | G28: Endpoints sin documentar. | H28: Colección Postman / documento de contrato vigente. | I28: Should | J28: Ambos | K28: — | L28: Restricción «Backend mandante» | M28: Revisión documental | N28: codigo/docs/postman/ | O28: Parcial | P28: Diego Madrid | Q28: DAS 1.0.2 restricción «Backend mandante» | R28: 04-requerimientos · Repo RNF-06.3 | S28: El DAS exige integración por contrato HTTP; la colección Postman es evidencia del catálogo.
A29: RNF-06.4 | B29: mantenibilidad | C29: Mantenibilidad | D29: Capacidad de prueba | E29: Lint y pruebas en verde (ID del catálogo) | F29: Todo PR debe pasar ESLint y la suite Jest antes de entrar a main. | G29: Errores de ESLint y tests fallidos. | H29: 0 errores ESLint; 0 tests fallidos. | I29: Should | J29: Ambos | K29: DoD código | L29: EC-RNF-05 (medida ESLint + DoD; el ID 06.4 no existe en el DAS) | M29: Jest suite | N29: D-01 App.test.tsx | O29: NOK | P29: Diego Madrid | Q29: Catálogo (deriva de DAS EC-RNF-05) | R29: Nuevo (no está en el DAS) | S29: El DAS mide «ESLint y Definition of Done del sprint»; no crea el ID RNF-06.4. Hoy falla App.test.tsx (D-01).
A30: RNF-07.1 | B30: escalabilidad | C30: Flexibilidad (Portabilidad) | D30: Escalabilidad | E30: Multi-tenant | F30: La plataforma debe aislar cada comercio en su propia base PostgreSQL. | G30: Tenants compartiendo BD. | H30: Un cliente = una BD. | I30: Must (plataforma) | J30: Plataforma DTemite | K30: — | L30: Capas de persistencia (PostgreSQL tenant; «un cliente = una BD» no está literal) | M30: — | N30: — | O30: N/A | P30: Diego Madrid | Q30: 04-requerimientos (fuera del literal del DAS) | R30: Repo RNF-07.1 · Fase 1 RNF-07.1 | S30: El DAS menciona base por comercio (PostgreSQL tenant). El criterio «un cliente = una BD» no está literal. Responsabilidad de plataforma; D-PAY lo consume.
... A33: RNF-08.2 | B33: cumplimiento | C33: Cumplimiento normativo (fuera de ISO 25010) | D33: PCI-DSS | E33: Tarjeta fuera de D-PAY | F33: D-PAY no debe procesar ni almacenar PAN en servidores propios; el dato de tarjeta queda en TUU o Transbank. | G33: Flujos donde D-PAY recibe PAN. | H33: 0 flujos con PAN en D-PAY o proxy. | I33: Must | J33: Ambos | K33: CA-WP.2 | L33: ADR-05 · ADR-07 | M33: TC-SEC | N33: Ver RNF-02.4 | O33: OK | P33: Reinhartd Munzenmayer | Q33: DAS 1.0.2 ADR-05 · ADR-07 | R33: 04-requerimientos · Repo RNF-08.3 | S33: Alineado con el DAS (tarjeta fuera de D-PAY). Complementa RNF-02.4.
A34: RNF-09.1 | B34: seguridad | C34: Seguridad | D34: Confidencialidad | E34: Repositorio público sin secretos | F34: El repositorio público no debe contener secretos ni datos productivos del mandante. | G34: Secretos detectados por escaneo. | H34: 0 hallazgos en escaneo de secretos. | I34: Must | J34: Ambos | K34: — | L34: Restricción «Confidencialidad académica» | M34: TC-SEC | N34: Auditoría COD-03 | O34: OK | P34: Reinhartd Munzenmayer | Q34: DAS 1.0.2 restricción «Confidencialidad académica» | R34: DoD v1.0 · Repo RNF-09.3
A35: RNF-09.2 | B35: operacion | C35: Flexibilidad (Portabilidad) | D35: Instalabilidad | E35: Entornos debug/QA y release/producción | F35: Las builds debug deben apuntar a QA (proqa.dtemite.cl) y las release a producción. | G35: Builds apuntando al entorno equivocado. | H35: Debug → QA; release → producción. | I35: Must | J35: Ambos | K35: — | L35: Meta Operatividad | M35: Revisión de configuración | N35: Manual DOC-05 | O35: OK | P35: Diego Madrid | Q35: DAS 1.0.2 Meta Operatividad (URLs no están en el DAS) | R35: 04-requerimientos · Repo RNF-09.1 | S35: Operacionalización del catálogo.
A36: RNF-09.3 | B36: operacion | C36: Flexibilidad (Portabilidad) | D36: Instalabilidad | E36: APK release reproducible | F36: El APK release debe poder generarse de forma documentada y reproducible. | G36: Pasos manuales fuera del procedimiento documentado. | H36: APK firmado generado con el procedimiento documentado. | I36: Must | J36: Ambos | K36: — | L36: Meta Operatividad | M36: Build | N36: APK debug v2.7.0 (19/09) | O36: Parcial | P36: Diego Madrid | Q36: DAS 1.0.2 Meta Operatividad (script/Docker no están en el DAS) | R36: 04-requerimientos · Repo RNF-09.2 | S36: «npm run build:apk» y «sin contenedores» ; son restricción de proyecto documentada en este catálogo. Debug validado en celular Android; release firmada pendiente S15.

Sheet Escenarios DAS
A1: Escenarios de calidad (DAS §Vista de escenarios)
A2: EC-RNF-01…05 vigentes en DAS 1.0.2 · EC-RNF-06…09 solo en este catálogo (fuera del DAS; el DAS no se modifica)
A4: ID | B4: Atributo | C4: Fuente del estímulo | D4: Estímulo | E4: Artefacto | F4: Ambiente | G4: Respuesta | H4: Medida | I4: RNF trazados | J4: Estado | K4: Observación
A5: EC-RNF-01 | B5: Usabilidad | C5: Cajero | D5: Cerrar venta con cliente esperando | E5: App D-PAY (flujo venta) | F5: Operación normal, pantalla 5"–6" | G5: Flujo con pocos toques y mensajes claros en español | H5: Venta efectivo + boleta en menos de 2 minutos en prueba guiada (texto DAS) | I5: RNF-04.2 · RNF-04.3 · RNF-04.1 | J5: Vigente (DAS 1.0.2) | K5: Fuente y Artefacto son de esta hoja (SEI). El DAS 1.0.2 no los trae y no se modifica.
A6: EC-RNF-02 | B6: Eficiencia de desempeño | C6: Cajero | D6: Confirmar venta con documento tributario | E6: Servicio de emisión DTE | F6: Red móvil estable (QA) | G6: Folio asignado y comprobante disponible | H6: Hasta 15 s desde confirmación hasta folio, promedio 5 muestras (texto DAS) | I6: RNF-01.4 | J6: Vigente (DAS 1.0.2) | K6: Se conserva «red móvil estable (QA)» del DAS. El entorno de prueba se documenta en DOC-07.
A7: EC-RNF-03 | B7: Seguridad | C7: Atacante con acceso al dispositivo | D7: Inspección de almacenamiento | E7: MMKV, SQLite proxy, repositorio | F7: (El DAS no declara Ambiente) | G7: Sin PAN/CVV persistidos; token no legible en texto plano | H7: Checklist de seguridad; ausencia de secretos en repositorio (texto DAS) | I7: RNF-02.1 · 02.2 · 02.4 · 02.5 · 09.1 | J7: Vigente (DAS 1.0.2) | K7: El catálogo cita DOC-07 04_Seguridad como checklist. El DAS no se modifica.
A8: EC-RNF-04 | B8: Disponibilidad | C8: Red móvil | D8: Pérdida de conectividad durante la venta | E8: Cola MMKV | F8: (El DAS no declara Ambiente) | G8: Venta en efectivo en cola local; DTE al recuperar red | H8: Caso de prueba definido; cero pérdida de carrito (texto DAS) | I8: RNF-03.1 | J8: Vigente (DAS 1.0.2) | K8: El catálogo operacionaliza la medida en TC-RNF03 (0 carritos). El DAS no se modifica.
A9: EC-RNF-05 | B9: Mantenibilidad | C9: Par revisor | D9: Revisión de código | E9: Repositorio dpay_3.0 | F9: (El DAS no declara Ambiente) | G9: Separación stores / services / screens; TypeScript estructurado | H9: ESLint y Definition of Done del sprint (texto DAS) | I9: RNF-06.1 · 06.2 · 06.4 | J9: Vigente (DAS 1.0.2) | K9: RNF-06.4 es ID del catálogo derivado de esta medida; el DAS no crea ese ID.
A10: EC-RNF-06 | B10: Compatibilidad / Portabilidad | C10: Cajero | D10: Abrir cobro con tarjeta | E10: PaymentGatewayFactory | F10: Kozen con TUU o celular genérico | G10: Ofrece TUU en Kozen y Webpay en genérico | H10: 100 % de selección correcta en tests de factory + smoke por perfil | I10: RNF-05.2 · RNF-05.3 · RNF-06.2 | J10: Fuera del DAS 1.0.2 | K10: Solo en este catálogo. El DAS describe Kozen/genérico en restricciones, sin escenario de calidad. El DAS no se modifica.
A11: EC-RNF-07 | B11: Fiabilidad (tolerancia a fallos) | C11: Proxy Webpay | D11: Proxy caído o sin URL | E11: Selector de pasarela | F11: Celular genérico | G11: Webpay no se ofrece o se informa que la tarjeta no está disponible | H11: 0 cobros iniciados contra proxy caído (CA-WP.5) | I11: RNF-03.2 | J11: Fuera del DAS 1.0.2 | K11: Solo en este catálogo (cubre DEF-NET / DEF-CFG). El DAS no se modifica.
A12: EC-RNF-08 | B12: Eficiencia de desempeño | C12: Cajero | D12: Confirmar monto con tarjeta | E12: Intent TUU | F12: Kozen P8 Neo en operación | G12: Pantalla TUU visible | H12: < 2 s (umbral DoD, no DAS) | I12: RNF-01.2 | J12: Fuera del DAS 1.0.2 | K12: Solo en este catálogo. Línea base D-PAY 2.0 (Diego). El DAS no se modifica.
A13: EC-RNF-09 | B13: Eficiencia de desempeño | C13: Cajero | D13: Confirmar pago Webpay | E13: webpay-proxy + Transbank | F13: Wi-Fi LAN con proxy | G13: Checkout Transbank abierto | H13: < 10 s, 5 muestras (umbral DoD, no DAS) | I13: RNF-01.5 | J13: Fuera del DAS 1.0.2 | K13: Solo en este catálogo. El DAS incluye Webpay sin umbral de 10 s. El DAS no se modifica.

Sheet Control
A1: Tablero de control RNF
A2: Conteos calculados desde la hoja Catálogo RNF
A4: Tipo | B4: OK | C4: Parcial | D4: NOK | E4: No ejecutado | F4: Bloqueado | G4: N/A | H4: Propuesto | I4: Total
A5: rendimiento | B5: =COUNTIFS('Catálogo RNF'!$B:$B,$A5,'Catálogo RNF'!$O:$O,"OK") | C5: =COUNTIFS('Catálogo RNF'!$B:$B,$A5,'Catálogo RNF'!$O:$O,"Parcial") | D5: =COUNTIFS('Catálogo RNF'!$B:$B,$A5,'Catálogo RNF'!$O:$O,"NOK") | E5: =COUNTIFS('Catálogo RNF'!$B:$B,$A5,'Catálogo RNF'!$O:$O,"No ejecutado") | F5: =COUNTIFS('Catálogo RNF'!$B:$B,$A5,'Catálogo RNF'!$O:$O,"Bloqueado") | G5: =COUNTIFS('Catálogo RNF'!$B:$B,$A5,'Catálogo RNF'!$O:$O,"N/A") | H5: =COUNTIFS('Catálogo RNF'!$B:$B,$A5,'Catálogo RNF'!$O:$O,"Propuesto") | I5: =SUM(B5:H5)
A6: seguridad | B6: =COUNTIFS('Catálogo RNF'!$B:$B,$A6,'Catálogo RNF'!$O:$O,"OK") | C6: =COUNTIFS('Catálogo RNF'!$B:$B,$A6,'Catálogo RNF'!$O:$O,"Parcial") | D6: =COUNTIFS('Catálogo RNF'!$B:$B,$A6,'Catálogo RNF'!$O:$O,"NOK") | E6: =COUNTIFS('Catálogo RNF'!$B:$B,$A6,'Catálogo RNF'!$O:$O,"No ejecutado") | F6: =COUNTIFS('Catálogo RNF'!$B:$B,$A6,'Catálogo RNF'!$O:$O,"Bloqueado") | G6: =COUNTIFS('Catálogo RNF'!$B:$B,$A6,'Catálogo RNF'!$O:$O,"N/A") | H6: =COUNTIFS('Catálogo RNF'!$B:$B,$A6,'Catálogo RNF'!$O:$O,"Propuesto") | I6: =SUM(B6:H6)
A7: disponibilidad | B7: =COUNTIFS('Catálogo RNF'!$B:$B,$A7,'Catálogo RNF'!$O:$O,"OK") | C7: =COUNTIFS('Catálogo RNF'!$B:$B,$A7,'Catálogo RNF'!$O:$O,"Parcial") | D7: =COUNTIFS('Catálogo RNF'!$B:$B,$A7,'Catálogo RNF'!$O:$O,"NOK") | E7: =COUNTIFS('Catálogo RNF'!$B:$B,$A7,'Catálogo RNF'!$O:$O,"No ejecutado") | F7: =COUNTIFS('Catálogo RNF'!$B:$B,$A7,'Catálogo RNF'!$O:$O,"Bloqueado") | G7: =COUNTIFS('Catálogo RNF'!$B:$B,$A7,'Catálogo RNF'!$O:$O,"N/A") | H7: =COUNTIFS('Catálogo RNF'!$B:$B,$A7,'Catálogo RNF'!$O:$O,"Propuesto") | I7: =SUM(B7:H7)
A8: usabilidad | B8: =COUNTIFS('Catálogo RNF'!$B:$B,$A8,'Catálogo RNF'!$O:$O,"OK") | C8: =COUNTIFS('Catálogo RNF'!$B:$B,$A8,'Catálogo RNF'!$O:$O,"Parcial") | D8: =COUNTIFS('Catálogo RNF'!$B:$B,$A8,'Catálogo RNF'!$O:$O,"NOK") | E8: =COUNTIFS('Catálogo RNF'!$B:$B,$A8,'Catálogo RNF'!$O:$O,"No ejecutado") | F8: =COUNTIFS('Catálogo RNF'!$B:$B,$A8,'Catálogo RNF'!$O:$O,"Bloqueado") | G8: =COUNTIFS('Catálogo RNF'!$B:$B,$A8,'Catálogo RNF'!$O:$O,"N/A") | H8: =COUNTIFS('Catálogo RNF'!$B:$B,$A8,'Catálogo RNF'!$O:$O,"Propuesto") | I8: =SUM(B8:H8)
A9: portabilidad | B9: =COUNTIFS('Catálogo RNF'!$B:$B,$A9,'Catálogo RNF'!$O:$O,"OK") | C9: =COUNTIFS('Catálogo RNF'!$B:$B,$A9,'Catálogo RNF'!$O:$O,"Parcial") | D9: =COUNTIFS('Catálogo RNF'!$B:$B,$A9,'Catálogo RNF'!$O:$O,"NOK") | E9: =COUNTIFS('Catálogo RNF'!$B:$B,$A9,'Catálogo RNF'!$O:$O,"No ejecutado") | F9: =COUNTIFS('Catálogo RNF'!$B:$B,$A9,'Catálogo RNF'!$O:$O,"Bloqueado") | G9: =COUNTIFS('Catálogo RNF'!$B:$B,$A9,'Catálogo RNF'!$O:$O,"N/A") | H9: =COUNTIFS('Catálogo RNF'!$B:$B,$A9,'Catálogo RNF'!$O:$O,"Propuesto") | I9: =SUM(B9:H9)
A10: mantenibilidad | B10: =COUNTIFS('Catálogo RNF'!$B:$B,$A10,'Catálogo RNF'!$O:$O,"OK") | C10: =COUNTIFS('Catálogo RNF'!$B:$B,$A10,'Catálogo RNF'!$O:$O,"Parcial") | D10: =COUNTIFS('Catálogo RNF'!$B:$B,$A10,'Catálogo RNF'!$O:$O,"NOK") | E10: =COUNTIFS('Catálogo RNF'!$B:$B,$A10,'Catálogo RNF'!$O:$O,"No ejecutado") | F10: =COUNTIFS('Catálogo RNF'!$B:$B,$A10,'Catálogo RNF'!$O:$O,"Bloqueado") | G10: =COUNTIFS('Catálogo RNF'!$B:$B,$A10,'Catálogo RNF'!$O:$O,"N/A") | H10: =COUNTIFS('Catálogo RNF'!$B:$B,$A10,'Catálogo RNF'!$O:$O,"Propuesto") | I10: =SUM(B10:H10)
A11: escalabilidad | B11: =COUNTIFS('Catálogo RNF'!$B:$B,$A11,'Catálogo RNF'!$O:$O,"OK") | C11: =COUNTIFS('Catálogo RNF'!$B:$B,$A11,'Catálogo RNF'!$O:$O,"Parcial") | D11: =COUNTIFS('Catálogo RNF'!$B:$B,$A11,'Catálogo RNF'!$O:$O,"NOK") | E11: =COUNTIFS('Catálogo RNF'!$B:$B,$A11,'Catálogo RNF'!$O:$O,"No ejecutado") | F11: =COUNTIFS('Catálogo RNF'!$B:$B,$A11,'Catálogo RNF'!$O:$O,"Bloqueado") | G11: =COUNTIFS('Catálogo RNF'!$B:$B,$A11,'Catálogo RNF'!$O:$O,"N/A") | H11: =COUNTIFS('Catálogo RNF'!$B:$B,$A11,'Catálogo RNF'!$O:$O,"Propuesto") | I11: =SUM(B11:H11)
A12: cumplimiento | B12: =COUNTIFS('Catálogo RNF'!$B:$B,$A12,'Catálogo RNF'!$O:$O,"OK") | C12: =COUNTIFS('Catálogo RNF'!$B:$B,$A12,'Catálogo RNF'!$O:$O,"Parcial") | D12: =COUNTIFS('Catálogo RNF'!$B:$B,$A12,'Catálogo RNF'!$O:$O,"NOK") | E12: =COUNTIFS('Catálogo RNF'!$B:$B,$A12,'Catálogo RNF'!$O:$O,"No ejecutado") | F12: =COUNTIFS('Catálogo RNF'!$B:$B,$A12,'Catálogo RNF'!$O:$O,"Bloqueado") | G12: =COUNTIFS('Catálogo RNF'!$B:$B,$A12,'Catálogo RNF'!$O:$O,"N/A") | H12: =COUNTIFS('Catálogo RNF'!$B:$B,$A12,'Catálogo RNF'!$O:$O,"Propuesto") | I12: =SUM(B12:H12)
A13: operacion | B13: =COUNTIFS('Catálogo RNF'!$B:$B,$A13,'Catálogo RNF'!$O:$O,"OK") | C13: =COUNTIFS('Catálogo RNF'!$B:$B,$A13,'Catálogo RNF'!$O:$O,"Parcial") | D13: =COUNTIFS('Catálogo RNF'!$B:$B,$A13,'Catálogo RNF'!$O:$O,"NOK") | E13: =COUNTIFS('Catálogo RNF'!$B:$B,$A13,'Catálogo RNF'!$O:$O,"No ejecutado") | F13: =COUNTIFS('Catálogo RNF'!$B:$B,$A13,'Catálogo RNF'!$O:$O,"Bloqueado") | G13: =COUNTIFS('Catálogo RNF'!$B:$B,$A13,'Catálogo RNF'!$O:$O,"N/A") | H13: =COUNTIFS('Catálogo RNF'!$B:$B,$A13,'Catálogo RNF'!$O:$O,"Propuesto") | I13: =SUM(B13:H13)
A14: Total | B14: =SUM(B5:B13) | C14: =SUM(C5:C13) | D14: =SUM(D5:D13) | E14: =SUM(E5:E13) | F14: =SUM(F5:F13) | G14: =SUM(G5:G13) | H14: =SUM(H5:H13) | I14: =SUM(I5:I13)
A16: RNF Must (incl. plataforma) | B16: =COUNTIF('Catálogo RNF'!$I:$I,"Must*")
A17: Must verificados OK | B17: =COUNTIFS('Catálogo RNF'!$I:$I,"Must*",'Catálogo RNF'!$O:$O,"OK")
A18: % Must OK | B18: =IFERROR(B17/B16,0)
A19: Must bloqueados (solo QA, línea 2.0) | B19: =COUNTIFS('Catálogo RNF'!$I:$I,"Must*",'Catálogo RNF'!$O:$O,"Bloqueado")
A20: % total OK | B20: =IFERROR(COUNTIF('Catálogo RNF'!$O:$O,"OK")/COUNTA('Catálogo RNF'!$A$5:$A$200),0)

Sheet Listas
A1: Tipo | B1: MoSCoW | C1: Alcance | D1: Estado
A2: rendimiento | B2: Must | C2: Ambos | D2: OK
A3: seguridad | B3: Must (plataforma) | C3: D-PAY 2.0 Kozen | D3: Parcial
A4: disponibilidad | B4: Should | C4: D-PAY 3.0 Capstone | D4: NOK
A5: usabilidad | B5: Could | C5: Plataforma DTemite | D5: No ejecutado
A6: portabilidad | B6: Won't | D6: Bloqueado
A7: mantenibilidad | D7: N/A
A8: escalabilidad | D8: Propuesto
A9: cumplimiento
A10: operacion
